Products.LocalFS-3.1-py3.11-nspkg.pth
Products/LocalFS/LocalFS.py
Products/LocalFS/StreamingFile.py
Products/LocalFS/__init__.py
Products/LocalFS/exceptions.py
Products/LocalFS/utils.py
Products/LocalFS/Extensions/Factory.py
Products/LocalFS/dtml/main.dtml
Products/LocalFS/dtml/methodAdd.dtml
Products/LocalFS/dtml/methodUpload.dtml
Products/LocalFS/tests/__init__.py
Products/LocalFS/tests/helpers.py
Products/LocalFS/tests/test_LocalDirectory.py
Products/LocalFS/tests/test_LocalFS.py
Products/LocalFS/tests/test_StreamingFile.py
Products/LocalFS/tests/test_utils.py
Products/LocalFS/tests/files/.gitkeep
Products/LocalFS/www/a.gif
Products/LocalFS/www/alert.black.gif
Products/LocalFS/www/alert.red.gif
Products/LocalFS/www/apache_pb.gif
Products/LocalFS/www/back.gif
Products/LocalFS/www/ball.gray.gif
Products/LocalFS/www/ball.red.gif
Products/LocalFS/www/binary.gif
Products/LocalFS/www/binhex.gif
Products/LocalFS/www/blank.gif
Products/LocalFS/www/bomb.gif
Products/LocalFS/www/box1.gif
Products/LocalFS/www/box2.gif
Products/LocalFS/www/broken.gif
Products/LocalFS/www/burst.gif
Products/LocalFS/www/c.gif
Products/LocalFS/www/comp.blue.gif
Products/LocalFS/www/comp.gray.gif
Products/LocalFS/www/compressed.gif
Products/LocalFS/www/continued.gif
Products/LocalFS/www/dir.gif
Products/LocalFS/www/down.gif
Products/LocalFS/www/dvi.gif
Products/LocalFS/www/f.gif
Products/LocalFS/www/folder.gif
Products/LocalFS/www/folder.open.gif
Products/LocalFS/www/folder.sec.gif
Products/LocalFS/www/forward.gif
Products/LocalFS/www/fs.gif
Products/LocalFS/www/generic.gif
Products/LocalFS/www/generic.red.gif
Products/LocalFS/www/generic.sec.gif
Products/LocalFS/www/hand.right.gif
Products/LocalFS/www/hand.up.gif
Products/LocalFS/www/icon.sheet.gif
Products/LocalFS/www/image1.gif
Products/LocalFS/www/image2.gif
Products/LocalFS/www/image3.gif
Products/LocalFS/www/index.gif
Products/LocalFS/www/layout.gif
Products/LocalFS/www/left.gif
Products/LocalFS/www/link.gif
Products/LocalFS/www/movie.gif
Products.LocalFS-3.1.dist-info/LICENSE.txt
Products.LocalFS-3.1.dist-info/METADATA
Products.LocalFS-3.1.dist-info/WHEEL
Products.LocalFS-3.1.dist-info/namespace_packages.txt
Products.LocalFS-3.1.dist-info/top_level.txt
Products.LocalFS-3.1.dist-info/RECORD
