Metadata-Version: 2.1
Name: Products.LocalFS
Version: 3.1
Summary: The Local File System product
Home-page: https://github.com/dataflake/Products.LocalFS
Author: Jonothan Farr and contributors
Author-email: jfarr@speakeasy.org
Maintainer: Jens Vagelpohl
Maintainer-email: jens@dataflake.org
License: BSD License
Project-URL: Documentation, https://productslocalfs.readthedocs.io/
Project-URL: Issue Tracker, https://github.com/dataflake/Products.LocalFS/issues
Project-URL: Sources, https://github.com/dataflake/Products.LocalFS
Keywords: web application server zope
Classifier: Development Status :: 6 - Mature
Classifier: Environment :: Web Environment
Classifier: Framework :: Zope
Classifier: Framework :: Zope :: 5
Classifier: Intended Audience :: Developers
Classifier: License :: OSI Approved :: BSD License
Classifier: Operating System :: OS Independent
Classifier: Programming Language :: Python
Classifier: Programming Language :: Python :: 3
Classifier: Programming Language :: Python :: 3.7
Classifier: Programming Language :: Python :: 3.8
Classifier: Programming Language :: Python :: 3.9
Classifier: Programming Language :: Python :: 3.10
Classifier: Programming Language :: Python :: 3.11
Classifier: Programming Language :: Python :: 3.12
Classifier: Topic :: Internet :: WWW/HTTP :: Site Management
Requires-Python: >=3.7
License-File: LICENSE.txt
Requires-Dist: setuptools
Requires-Dist: Zope >=5
Requires-Dist: Products.PythonScripts
Provides-Extra: docs
Requires-Dist: Sphinx ; extra == 'docs'
Requires-Dist: sphinx-rtd-theme ; extra == 'docs'
Requires-Dist: pkginfo ; extra == 'docs'
